{"Monday":[{"id":"1324","title":"453456346","date":"2015-12-31","start":"2015-12-31T00:00:00","end":"2015-12-31T00:00:00","class":"","plan":"sdf","monday":"1","tuesday":"1","wednesday":"1","thursday":"1","friday":"0","saturday":"1","sunday":"1"},{"id":"1325","title":"React View Change","date":"2016-01-06","start":"2016-01-06T01:00:00","end":"2016-01-06T09:00:00","class":"WOAH CLASS","plan":"REACT PLAN","monday":"1","tuesday":"1","wednesday":"1","thursday":"0","friday":"0","saturday":"1","sunday":"0"},{"id":"1326","title":"Switch out the datetimepicker?","date":"2016-01-06","start":"2016-01-06T09:00:00","end":"2016-01-06T13:00:00","class":"WOAH CLASS","plan":"REACT PLAN","monday":"1","tuesday":"1","wednesday":"1","thursday":"0","friday":"0","saturday":"1","sunday":"0"},{"id":"1327","title":"Browserfy packages.","date":"2016-01-06","start":"2016-01-06T13:00:00","end":"2016-01-06T18:00:00","class":"WOAH CLASS","plan":"REACT PLAN","monday":"1","tuesday":"1","wednesday":"1","thursday":"0","friday":"0","saturday":"1","sunday":"0"},{"id":"1328","title":"Consolidate files that cant be browserfied","date":"2016-01-06","start":"2016-01-06T18:00:00","end":"2016-01-06T20:00:00","class":"WOAH CLASS","plan":"REACT PLAN","monday":"1","tuesday":"1","wednesday":"1","thursday":"0","friday":"0","saturday":"1","sunday":"0"},{"id":"1329","title":"test mobile views","date":"2016-01-06","start":"2016-01-06T20:00:00","end":"2016-01-06T23:00:00","class":"WOAH CLASS","plan":"REACT PLAN","monday":"1","tuesday":"1","wednesday":"1","thursday":"0","friday":"0","saturday":"1","sunday":"0"},{"id":"1330","title":"cordova and react together...or go with react native","date":"2016-01-06","start":"2016-01-06T23:00:00","end":"2016-01-06T23:55:00","class":"WOAH CLASS","plan":"REACT PLAN","monday":"1","tuesday":"1","wednesday":"1","thursday":"0","friday":"0","saturday":"1","sunday":"0"},{"id":"1331","title":"testing futher changes...","date":"2016-01-06","start":"2016-01-06T02:00:00","end":"2016-01-06T06:00:00","class":"34","plan":"SAME DAY plan","monday":"1","tuesday":"0","wednesday":"1","thursday":"0","friday":"1","saturday":"0","sunday":"0"},{"id":"1332","title":"detect collisions in time and delete or something","date":"2016-01-06","start":"2016-01-06T06:00:00","end":"2016-01-06T12:00:00","class":"34","plan":"SAME DAY plan","monday":"1","tuesday":"0","wednesday":"1","thursday":"0","friday":"1","saturday":"0","sunday":"0"},{"id":"1333","title":"make easier to thumb buttons and such","date":"2016-01-06","start":"2016-01-06T12:00:00","end":"2016-01-06T17:00:00","class":"34","plan":"SAME DAY plan","monday":"1","tuesday":"0","wednesday":"1","thursday":"0","friday":"1","saturday":"0","sunday":"0"},{"id":"1334","title":"add google calendar plugin","date":"2016-01-06","start":"2016-01-06T17:00:00","end":"2016-01-06T22:00:00","class":"34","plan":"SAME DAY plan","monday":"1","tuesday":"0","wednesday":"1","thursday":"0","friday":"1","saturday":"0","sunday":"0"}],"Tuesday":[{"id":"1324","title":"453456346","date":"2015-12-31","start":"2015-12-31T00:00:00","end":"2015-12-31T00:00:00","class":"","plan":"sdf","monday":"1","tuesday":"1","wednesday":"1","thursday":"1","friday":"0","saturday":"1","sunday":"1"},{"id":"1325","title":"React View Change","date":"2016-01-06","start":"2016-01-06T01:00:00","end":"2016-01-06T09:00:00","class":"WOAH CLASS","plan":"REACT PLAN","monday":"1","tuesday":"1","wednesday":"1","thursday":"0","friday":"0","saturday":"1","sunday":"0"},{"id":"1326","title":"Switch out the datetimepicker?","date":"2016-01-06","start":"2016-01-06T09:00:00","end":"2016-01-06T13:00:00","class":"WOAH CLASS","plan":"REACT PLAN","monday":"1","tuesday":"1","wednesday":"1","thursday":"0","friday":"0","saturday":"1","sunday":"0"},{"id":"1327","title":"Browserfy packages.","date":"2016-01-06","start":"2016-01-06T13:00:00","end":"2016-01-06T18:00:00","class":"WOAH CLASS","plan":"REACT PLAN","monday":"1","tuesday":"1","wednesday":"1","thursday":"0","friday":"0","saturday":"1","sunday":"0"},{"id":"1328","title":"Consolidate files that cant be browserfied","date":"2016-01-06","start":"2016-01-06T18:00:00","end":"2016-01-06T20:00:00","class":"WOAH CLASS","plan":"REACT PLAN","monday":"1","tuesday":"1","wednesday":"1","thursday":"0","friday":"0","saturday":"1","sunday":"0"},{"id":"1329","title":"test mobile views","date":"2016-01-06","start":"2016-01-06T20:00:00","end":"2016-01-06T23:00:00","class":"WOAH CLASS","plan":"REACT PLAN","monday":"1","tuesday":"1","wednesday":"1","thursday":"0","friday":"0","saturday":"1","sunday":"0"},{"id":"1330","title":"cordova and react together...or go with react native","date":"2016-01-06","start":"2016-01-06T23:00:00","end":"2016-01-06T23:55:00","class":"WOAH CLASS","plan":"REACT PLAN","monday":"1","tuesday":"1","wednesday":"1","thursday":"0","friday":"0","saturday":"1","sunday":"0"}],"Wednesday":[{"id":"1324","title":"453456346","date":"2015-12-31","start":"2015-12-31T00:00:00","end":"2015-12-31T00:00:00","class":"","plan":"sdf","monday":"1","tuesday":"1","wednesday":"1","thursday":"1","friday":"0","saturday":"1","sunday":"1"},{"id":"1325","title":"React View Change","date":"2016-01-06","start":"2016-01-06T01:00:00","end":"2016-01-06T09:00:00","class":"WOAH CLASS","plan":"REACT PLAN","monday":"1","tuesday":"1","wednesday":"1","thursday":"0","friday":"0","saturday":"1","sunday":"0"},{"id":"1326","title":"Switch out the datetimepicker?","date":"2016-01-06","start":"2016-01-06T09:00:00","end":"2016-01-06T13:00:00","class":"WOAH CLASS","plan":"REACT PLAN","monday":"1","tuesday":"1","wednesday":"1","thursday":"0","friday":"0","saturday":"1","sunday":"0"},{"id":"1327","title":"Browserfy packages.","date":"2016-01-06","start":"2016-01-06T13:00:00","end":"2016-01-06T18:00:00","class":"WOAH CLASS","plan":"REACT PLAN","monday":"1","tuesday":"1","wednesday":"1","thursday":"0","friday":"0","saturday":"1","sunday":"0"},{"id":"1328","title":"Consolidate files that cant be browserfied","date":"2016-01-06","start":"2016-01-06T18:00:00","end":"2016-01-06T20:00:00","class":"WOAH CLASS","plan":"REACT PLAN","monday":"1","tuesday":"1","wednesday":"1","thursday":"0","friday":"0","saturday":"1","sunday":"0"},{"id":"1329","title":"test mobile views","date":"2016-01-06","start":"2016-01-06T20:00:00","end":"2016-01-06T23:00:00","class":"WOAH CLASS","plan":"REACT PLAN","monday":"1","tuesday":"1","wednesday":"1","thursday":"0","friday":"0","saturday":"1","sunday":"0"},{"id":"1330","title":"cordova and react together...or go with react native","date":"2016-01-06","start":"2016-01-06T23:00:00","end":"2016-01-06T23:55:00","class":"WOAH CLASS","plan":"REACT PLAN","monday":"1","tuesday":"1","wednesday":"1","thursday":"0","friday":"0","saturday":"1","sunday":"0"},{"id":"1331","title":"testing futher changes...","date":"2016-01-06","start":"2016-01-06T02:00:00","end":"2016-01-06T06:00:00","class":"34","plan":"SAME DAY plan","monday":"1","tuesday":"0","wednesday":"1","thursday":"0","friday":"1","saturday":"0","sunday":"0"},{"id":"1332","title":"detect collisions in time and delete or something","date":"2016-01-06","start":"2016-01-06T06:00:00","end":"2016-01-06T12:00:00","class":"34","plan":"SAME DAY plan","monday":"1","tuesday":"0","wednesday":"1","thursday":"0","friday":"1","saturday":"0","sunday":"0"},{"id":"1333","title":"make easier to thumb buttons and such","date":"2016-01-06","start":"2016-01-06T12:00:00","end":"2016-01-06T17:00:00","class":"34","plan":"SAME DAY plan","monday":"1","tuesday":"0","wednesday":"1","thursday":"0","friday":"1","saturday":"0","sunday":"0"},{"id":"1334","title":"add google calendar plugin","date":"2016-01-06","start":"2016-01-06T17:00:00","end":"2016-01-06T22:00:00","class":"34","plan":"SAME DAY plan","monday":"1","tuesday":"0","wednesday":"1","thursday":"0","friday":"1","saturday":"0","sunday":"0"}],"Thursday":[{"id":"1324","title":"453456346","date":"2015-12-31","start":"2015-12-31T00:00:00","end":"2015-12-31T00:00:00","class":"","plan":"sdf","monday":"1","tuesday":"1","wednesday":"1","thursday":"1","friday":"0","saturday":"1","sunday":"1"}],"Friday":[{"id":"1331","title":"testing futher changes...","date":"2016-01-06","start":"2016-01-06T02:00:00","end":"2016-01-06T06:00:00","class":"34","plan":"SAME DAY plan","monday":"1","tuesday":"0","wednesday":"1","thursday":"0","friday":"1","saturday":"0","sunday":"0"},{"id":"1332","title":"detect collisions in time and delete or something","date":"2016-01-06","start":"2016-01-06T06:00:00","end":"2016-01-06T12:00:00","class":"34","plan":"SAME DAY plan","monday":"1","tuesday":"0","wednesday":"1","thursday":"0","friday":"1","saturday":"0","sunday":"0"},{"id":"1333","title":"make easier to thumb buttons and such","date":"2016-01-06","start":"2016-01-06T12:00:00","end":"2016-01-06T17:00:00","class":"34","plan":"SAME DAY plan","monday":"1","tuesday":"0","wednesday":"1","thursday":"0","friday":"1","saturday":"0","sunday":"0"},{"id":"1334","title":"add google calendar plugin","date":"2016-01-06","start":"2016-01-06T17:00:00","end":"2016-01-06T22:00:00","class":"34","plan":"SAME DAY plan","monday":"1","tuesday":"0","wednesday":"1","thursday":"0","friday":"1","saturday":"0","sunday":"0"}],"Saturday":[{"id":"1324","title":"453456346","date":"2015-12-31","start":"2015-12-31T00:00:00","end":"2015-12-31T00:00:00","class":"","plan":"sdf","monday":"1","tuesday":"1","wednesday":"1","thursday":"1","friday":"0","saturday":"1","sunday":"1"},{"id":"1325","title":"React View Change","date":"2016-01-06","start":"2016-01-06T01:00:00","end":"2016-01-06T09:00:00","class":"WOAH CLASS","plan":"REACT PLAN","monday":"1","tuesday":"1","wednesday":"1","thursday":"0","friday":"0","saturday":"1","sunday":"0"},{"id":"1326","title":"Switch out the datetimepicker?","date":"2016-01-06","start":"2016-01-06T09:00:00","end":"2016-01-06T13:00:00","class":"WOAH CLASS","plan":"REACT PLAN","monday":"1","tuesday":"1","wednesday":"1","thursday":"0","friday":"0","saturday":"1","sunday":"0"},{"id":"1327","title":"Browserfy packages.","date":"2016-01-06","start":"2016-01-06T13:00:00","end":"2016-01-06T18:00:00","class":"WOAH CLASS","plan":"REACT PLAN","monday":"1","tuesday":"1","wednesday":"1","thursday":"0","friday":"0","saturday":"1","sunday":"0"},{"id":"1328","title":"Consolidate files that cant be browserfied","date":"2016-01-06","start":"2016-01-06T18:00:00","end":"2016-01-06T20:00:00","class":"WOAH CLASS","plan":"REACT PLAN","monday":"1","tuesday":"1","wednesday":"1","thursday":"0","friday":"0","saturday":"1","sunday":"0"},{"id":"1329","title":"test mobile views","date":"2016-01-06","start":"2016-01-06T20:00:00","end":"2016-01-06T23:00:00","class":"WOAH CLASS","plan":"REACT PLAN","monday":"1","tuesday":"1","wednesday":"1","thursday":"0","friday":"0","saturday":"1","sunday":"0"},{"id":"1330","title":"cordova and react together...or go with react native","date":"2016-01-06","start":"2016-01-06T23:00:00","end":"2016-01-06T23:55:00","class":"WOAH CLASS","plan":"REACT PLAN","monday":"1","tuesday":"1","wednesday":"1","thursday":"0","friday":"0","saturday":"1","sunday":"0"}],"Sunday":[{"id":"1324","title":"453456346","date":"2015-12-31","start":"2015-12-31T00:00:00","end":"2015-12-31T00:00:00","class":"","plan":"sdf","monday":"1","tuesday":"1","wednesday":"1","thursday":"1","friday":"0","saturday":"1","sunday":"1"}]}